gracken/__init__.py
gracken/data_loaders.py
gracken/gracken.py
gracken/gtdb_utils.py
gracken/ncbi_utils.py
gracken/vars.py
gracken-0.1.1.dist-info/licenses/LICENSE
gracken-0.1.1.dist-info/METADATA
gracken-0.1.1.dist-info/WHEEL
gracken-0.1.1.dist-info/entry_points.txt
gracken-0.1.1.dist-info/top_level.txt
gracken-0.1.1.dist-info/RECORD
