Metadata-Version: 2.4
Name: gracken
Version: 0.1.1
Summary: Create phylogenetic trees from metagenomic reports.
Classifier: Programming Language :: Python :: 3
Classifier: Operating System :: OS Independent
Classifier: Topic :: Scientific/Engineering :: Bio-Informatics
Classifier: License :: OSI Approved :: MIT License
Classifier: Development Status :: 3 - Alpha
Classifier: Intended Audience :: Science/Research
Classifier: Environment :: Console
Requires-Python: >=3.9, <3.13
License-File: LICENSE
Requires-Dist: ete3==3.1.3
Requires-Dist: pandas==2.2.3
Dynamic: classifier
Dynamic: description
Dynamic: description-content-type
Dynamic: license-file
Dynamic: requires-dist
Dynamic: requires-python
Dynamic: summary
